brainyflow.py
brainyflow-2.1.0.dist-info/METADATA
brainyflow-2.1.0.dist-info/WHEEL
brainyflow-2.1.0.dist-info/top_level.txt
brainyflow-2.1.0.dist-info/RECORD
